pidgy/README.md
pidgy/__init__.py
pidgy/__main__.py
pidgy/_version.py
pidgy/current.py
pidgy/displays.py
pidgy/environment.py
pidgy/extras.py
pidgy/filters.py
pidgy/inspect.py
pidgy/kernel.py
pidgy/loader.py
pidgy/magics.py
pidgy/tangle.py
pidgy/weave.py
pidgy/ext/mkdocs.py
pidgy/ext/templates/ipynb.md.j2
pidgy/help/mermaid.md
pidgy/help/pidgy.md
pidgy/kernel/__init__.py
pidgy/kernel/__main__.py
pidgy-2023.4.20.data/data/share/jupyter/kernels/pidgy/kernel.json
pidgy-2023.4.20.data/data/share/jupyter/kernels/pidgy/logo-32x32.png
pidgy-2023.4.20.data/data/share/jupyter/kernels/pidgy/logo-64x64.png
pidgy-2023.4.20.dist-info/METADATA
pidgy-2023.4.20.dist-info/WHEEL
pidgy-2023.4.20.dist-info/entry_points.txt
pidgy-2023.4.20.dist-info/licenses/LICENSE
pidgy-2023.4.20.dist-info/RECORD
