Metadata-Version: 2.1
Name: pidgy
Version: 2023.4.20
Summary: literate computing in python
Project-URL: Documentation, https://github.com/deathbeds/pidgy#readme
Project-URL: Issues, https://github.com/deathbeds/pidgy/issues
Project-URL: Source, https://github.com/deathbeds/pidgy
Author-email: tonyfast <tony.fast@gmail.com>
License-Expression: BSD-3-Clause
License-File: LICENSE
Classifier: Development Status :: 4 - Beta
Classifier: Framework :: IPython
Classifier: Framework :: Jupyter
Classifier: License :: OSI Approved :: BSD License
Classifier: Natural Language :: English
Classifier: Programming Language :: Python
Requires-Python: >=3.7
Requires-Dist: importnb
Requires-Dist: ipython
Requires-Dist: jinja2
Requires-Dist: midgy
Provides-Extra: docs
Requires-Dist: mkdocs-material; extra == 'docs'
Requires-Dist: mkdocstrings[python]; extra == 'docs'
Requires-Dist: nbconvert; extra == 'docs'
Requires-Dist: ruamel-yaml; extra == 'docs'
Provides-Extra: lite
Requires-Dist: cairosvg; extra == 'lite'
Requires-Dist: depfinder; extra == 'lite'
Requires-Dist: doit; extra == 'lite'
Requires-Dist: hatch; extra == 'lite'
Requires-Dist: ipympl; extra == 'lite'
Requires-Dist: ipywidgets; extra == 'lite'
Requires-Dist: jupyter-videochat; extra == 'lite'
Requires-Dist: jupyterlab-deck; extra == 'lite'
Requires-Dist: jupyterlab-execute-time; extra == 'lite'
Requires-Dist: jupyterlab-fonts; extra == 'lite'
Requires-Dist: jupyterlab-markup; extra == 'lite'
Requires-Dist: jupyterlab-recents; extra == 'lite'
Requires-Dist: jupyterlab-webrtc-docprovider; extra == 'lite'
Requires-Dist: jupyterlite; extra == 'lite'
Requires-Dist: matplotlib; extra == 'lite'
Requires-Dist: pandas; extra == 'lite'
Requires-Dist: pillow; extra == 'lite'
Requires-Dist: pkginfo; extra == 'lite'
Requires-Dist: pyyaml; extra == 'lite'
Requires-Dist: requests-cache; extra == 'lite'
Requires-Dist: retrolab; extra == 'lite'
